snosearch/__init__.py
snosearch/configs.py
snosearch/decorators.py
snosearch/defaults.py
snosearch/fields.py
snosearch/interfaces.py
snosearch/mixins.py
snosearch/parsers.py
snosearch/queries.py
snosearch/responses.py
snosearch/adapters/__init__.py
snosearch/adapters/configs.py
snosearch/adapters/exceptions.py
snosearch/adapters/responses.py
snosearch/adapters/types.py
snosearch/adapters/flask/__init__.py
snosearch/adapters/flask/requests.py
snosearch/adapters/flask/responses.py
snosearch/tests/__init__.py
snosearch/tests/conftest.py
snosearch/tests/dummy_requests.py
snosearch/tests/test_searches_adapters_requests.py
snosearch/tests/test_searches_adapters_responses.py
snosearch/tests/test_searches_configs.py
snosearch/tests/test_searches_decorators.py
snosearch/tests/test_searches_fields.py
snosearch/tests/test_searches_mixins.py
snosearch/tests/test_searches_parsers.py
snosearch/tests/test_searches_queries.py
snosearch/tests/test_searches_responses.py
snovault_search-6.1.0.dist-info/LICENSE
snovault_search-6.1.0.dist-info/METADATA
snovault_search-6.1.0.dist-info/WHEEL
snovault_search-6.1.0.dist-info/top_level.txt
snovault_search-6.1.0.dist-info/RECORD
